easy_torch-1.3.3.dist-info/licenses/LICENSE
easytorch/__init__.py
easytorch/device.py
easytorch/version.py
easytorch/config/__init__.py
easytorch/config/config.py
easytorch/config/utils.py
easytorch/core/__init__.py
easytorch/core/checkpoint.py
easytorch/core/data_loader.py
easytorch/core/meter_pool.py
easytorch/core/optimizer_builder.py
easytorch/core/runner.py
easytorch/easyoptim/__init__.py
easytorch/easyoptim/easy_lr_scheduler.py
easytorch/easyoptim/lamb.py
easytorch/entry_points/__init__.py
easytorch/entry_points/easytrain.py
easytorch/launcher/__init__.py
easytorch/launcher/dist_wrap.py
easytorch/launcher/launcher.py
easytorch/utils/__init__.py
easytorch/utils/data_prefetcher.py
easytorch/utils/dist.py
easytorch/utils/env.py
easytorch/utils/logging.py
easytorch/utils/misc.py
easytorch/utils/named_hook.py
easytorch/utils/registry.py
easytorch/utils/timer.py
easy_torch-1.3.3.dist-info/METADATA
easy_torch-1.3.3.dist-info/WHEEL
easy_torch-1.3.3.dist-info/entry_points.txt
easy_torch-1.3.3.dist-info/top_level.txt
easy_torch-1.3.3.dist-info/RECORD
