Metadata-Version: 2.4
Name: easy-torch
Version: 1.3.3
Summary: Simple and powerful pytorch framework.
Home-page: https://github.com/cnstark/easytorch
Author: Yuhao Wang
Author-email: yuhaow97@gmail.com
License: Apache License 2.0
Keywords: pytorch,deep learning
Classifier: License :: OSI Approved :: Apache Software License
Classifier: Operating System :: OS Independent
Classifier: Programming Language :: Python :: 3
Classifier: Programming Language :: Python :: 3.7
Classifier: Programming Language :: Python :: 3.8
Classifier: Programming Language :: Python :: 3.9
Classifier: Topic :: Utilities
License-File: LICENSE
Requires-Dist: torch>=1.4
Requires-Dist: tensorboard
Requires-Dist: tqdm
Dynamic: author
Dynamic: author-email
Dynamic: classifier
Dynamic: description
Dynamic: description-content-type
Dynamic: home-page
Dynamic: keywords
Dynamic: license
Dynamic: license-file
Dynamic: requires-dist
Dynamic: summary
